apx/__init__.py
apx/auth.py
apx/config.py
apx/exceptions.py
apx/helpers.py
apx/param.py
apx/route.py
FlaskApx-1.0.1.dist-info/METADATA
FlaskApx-1.0.1.dist-info/WHEEL
FlaskApx-1.0.1.dist-info/top_level.txt
FlaskApx-1.0.1.dist-info/RECORD
