Metadata-Version: 2.1
Name: FlaskApx
Version: 1.0.1
Summary: The helper for Flask
Home-page: https://github.com/Nux-xader/Flask-Apx
Author: Nux xader A.K.A Satria Rahmat
Project-URL: Github, https://github.com/Nux-xader/Flask-Apx
Keywords: flask helper,flask,API heler,API Toolkit,API warper
Requires-Python: >=3.7, <4
Requires-Dist: flask
Requires-Dist: PyJWT ==2.7.0
